tags/__init__.py
tags/_version.py
tags/plugin.py
tags/templates/tags.md.template
mkdocs_plugin_tags-1.0.2.dist-info/LICENSE.md
mkdocs_plugin_tags-1.0.2.dist-info/METADATA
mkdocs_plugin_tags-1.0.2.dist-info/WHEEL
mkdocs_plugin_tags-1.0.2.dist-info/entry_points.txt
mkdocs_plugin_tags-1.0.2.dist-info/top_level.txt
mkdocs_plugin_tags-1.0.2.dist-info/RECORD
