Metadata-Version: 2.1
Name: mkdocs-plugin-tags
Version: 1.0.2
Summary: "Create tags in mkdocs"
Home-page: https://github.com/ginsburgnm/mkdocs-plugin-tags
Author: nginsburg
Author-email: ginsburgnm@gmail.com
License: MIT
Keywords: "mkdocs python markdown tags"
Platform: UNKNOWN
Classifier: Intended Audience :: Developers
Classifier: License :: OSI Approved :: MIT License
Classifier: Operating System :: OS Independent
Classifier: Intended Audience :: Information Technology
Classifier: Programming Language :: Python :: 3.6
Classifier: Programming Language :: Python :: 3.7
Classifier: Programming Language :: Python :: 3.8
Classifier: Topic :: Security :: Cryptography
Requires-Python: >=3.6
License-File: LICENSE.md
